fedex/__init__.py
fedex/base_service.py
fedex/config.py
fedex/printers/__init__.py
fedex/printers/unix.py
fedex/services/__init__.py
fedex/services/address_validation_service.py
fedex/services/availability_commitment_service.py
fedex/services/country_service.py
fedex/services/document_service.py
fedex/services/location_service.py
fedex/services/package_movement.py
fedex/services/pickup_service.py
fedex/services/rate_service.py
fedex/services/ship_service.py
fedex/services/track_service.py
fedex/tools/__init__.py
fedex/tools/conversion.py
fedex/wsdl/AddressValidationService_v4.wsdl
fedex/wsdl/CountryService_v8.wsdl
fedex/wsdl/LocationsService_v9.wsdl
fedex/wsdl/PackageMovementInformationService_v4.wsdl
fedex/wsdl/PickupService_v17.wsdl
fedex/wsdl/RateService_v24.wsdl
fedex/wsdl/ShipService_v23.wsdl
fedex/wsdl/TrackService_v16.wsdl
fedex/wsdl/UploadDocumentService_v11.wsdl
fedex/wsdl/ValidationAvailabilityAndCommitmentService_v8.wsdl
fedex/wsdl/test_server_wsdl/AddressValidationService_v4.wsdl
fedex/wsdl/test_server_wsdl/CountryService_v8.wsdl
fedex/wsdl/test_server_wsdl/LocationsService_v9.wsdl
fedex/wsdl/test_server_wsdl/PackageMovementInformationService_v4.wsdl
fedex/wsdl/test_server_wsdl/PickupService_v17.wsdl
fedex/wsdl/test_server_wsdl/RateService_v24.wsdl
fedex/wsdl/test_server_wsdl/ShipService_v23.wsdl
fedex/wsdl/test_server_wsdl/TrackService_v16.wsdl
fedex/wsdl/test_server_wsdl/UploadDocumentService_v11.wsdl
fedex/wsdl/test_server_wsdl/ValidationAvailabilityAndCommitmentService_v8.wsdl
ncswash_fedex-2.4.1.dist-info/LICENSE.txt
ncswash_fedex-2.4.1.dist-info/METADATA
ncswash_fedex-2.4.1.dist-info/WHEEL
ncswash_fedex-2.4.1.dist-info/top_level.txt
ncswash_fedex-2.4.1.dist-info/RECORD
