Metadata-Version: 2.1
Name: ncswash-fedex
Version: 2.4.1
Summary: Fedex Web Services API wrapper.
Home-page: https://github.com/python-fedex-devs/python-fedex
Download-URL: http://pypi.python.org/pypi/fedex/
Author: Greg Taylor
Author-email: gtaylor@gc-taylor.com
Maintainer: Nick Joyce
Maintainer-email: nick@stratuscode.com
License: BSD
Keywords: fedex soap suds wrapper rate track avs location ship pickup country availability commitment package service
Platform: Platform Independent
Classifier: Development Status :: 5 - Production/Stable
Classifier: Intended Audience :: Developers
Classifier: License :: OSI Approved :: BSD License
Classifier: Natural Language :: English
Classifier: Operating System :: OS Independent
Classifier: Programming Language :: Python
Classifier: Topic :: Software Development :: Libraries :: Python Modules
Requires: suds
License-File: LICENSE.txt
Requires-Dist: suds-community
